[{"type": "classroom", "priority": "SKIP", "summary": "thank you noise", "description": "[SKIP] thank you noise", "transcript": "Thank you.", "time": "2026-05-02T17:45:41.849079+00:00"}, {"type": "vision", "description": "You are in a room with white walls and a brown trim. There is a person sitting behind you and a laptop to your left; no immediate walking hazards are visible.", "time": "2026-05-02T17:45:55.732534+00:00"}, {"type": "vision", "description": "You are in a room with white walls and brown trim, similar to the area you were in 0 minutes ago. There are people sitting around you, and a laptop to your left; no immediate walking hazards are visible.", "time": "2026-05-02T17:46:02.178781+00:00"}, {"type": "vision", "description": "You appear to be indoors, with a white wall directly in front of you. There are no immediate hazards like stairs or obstacles visible.", "time": "2026-05-02T17:48:00.420379+00:00"}, {"type": "classroom", "priority": "NOTES", "summary": "Friction in physics lecture explained", "description": "[NOTES] Friction in physics lecture explained", "transcript": "ok so hello everyone I am Dixchel and today we are going to talk about the motion and types of motion what is friction in today's physics class you will be able to learn and identify what is actually motion how it works and this is also come in your exam so you should prepare it carefully after the exam your result will be announced on 28th of May 2026 so you should bring your parents here too all right I hope you have got my point And so what is friction? A force which opposes the motion of an object is called friction, right? I hope you are getting my point and let's end this.", "time": "2026-05-02T17:49:12.179756+00:00"}, {"type": "classroom", "priority": "URGENT", "summary": "Class stop command given", "description": "[URGENT] Class stop command given", "transcript": "Stop Stop", "time": "2026-05-02T17:49:32.036128+00:00"}, {"type": "sos", "description": "CLASSROOM URGENT: Class stop command given", "time": "2026-05-02T17:49:32.036128+00:00"}, {"type": "vision", "description": "You are in a room with white walls and brown trim. There are people and office equipment around you, but no immediate walking hazards are visible directly in front of you.", "time": "2026-05-02T17:53:35.594155+00:00"}, {"type": "vision", "description": "You are in an office setting with white walls and brown trim, similar to the area you were in a few minutes ago. There are no immediate walking hazards visible directly in front of you. What would you like to do next?", "time": "2026-05-02T17:53:42.568664+00:00"}, {"type": "geofence", "description": "⚠️ LEFT SAFE ZONE — Home (800m away)", "lat": 28.62, "lon": 77.21, "time": "2026-05-02T18:31:58.444800+00:00"}, {"type": "sos", "lat": "28.6139", "lon": "77.2090", "photo": null, "medical_info": {"allergies": "", "blood_type": "", "conditions": "", "emergency_notes": ""}, "description": "SOS at (28.6139,77.2090)", "time": "2026-05-02T18:32:10.683905+00:00"}, {"type": "care_update", "description": "Guardian updated care profile", "time": "2026-05-02T18:32:30.323191+00:00"}, {"type": "vision", "description": "You are in a room with several people around you. There are no immediate hazards like stairs or obstacles directly in front of you.", "time": "2026-05-02T18:41:25.107173+00:00"}, {"type": "classroom", "priority": "URGENT", "summary": "Stop immediately", "description": "[URGENT] Stop immediately", "transcript": "Stop!", "time": "2026-05-02T18:42:03.356743+00:00"}, {"type": "sos", "description": "CLASSROOM URGENT: Stop immediately", "time": "2026-05-02T18:42:03.356743+00:00"}, {"type": "vision", "description": "You are in a room with several people around you. There is a person directly in front of you, and another to your left; be cautious not to bump into them. The floor appears clear right in front of you.", "time": "2026-05-02T19:06:52.695073+00:00"}, {"type": "classroom", "priority": "URGENT", "summary": "Classroom stop command given", "description": "[URGENT] Classroom stop command given", "transcript": "Stop!", "time": "2026-05-02T19:07:25.478558+00:00"}, {"type": "sos", "description": "CLASSROOM URGENT: Classroom stop command given", "time": "2026-05-02T19:07:25.478558+00:00"}, {"type": "vision", "description": "You are in a room with white walls and a ceiling with lights. There are people around you, but no immediate obstacles or hazards are in your path. You appear to be seated.", "time": "2026-05-02T19:07:51.178032+00:00"}, {"type": "sos", "lat": "22.032373", "lon": "75.657845", "photo": null, "medical_info": {"blood_type": "B+", "allergies": "Peanuts", "conditions": "Asthma", "emergency_notes": "Carry inhaler"}, "description": "SOS at (22.032373,75.657845)", "time": "2026-05-02T19:07:53.173163+00:00"}, {"type": "sos", "lat": "22.032373", "lon": "75.657845", "photo": null, "medical_info": {"blood_type": "B+", "allergies": "Peanuts", "conditions": "Asthma", "emergency_notes": "Carry inhaler"}, "description": "SOS at (22.032373,75.657845)", "time": "2026-05-02T19:07:53.175506+00:00"}, {"type": "vision", "description": "You are in a room with white walls and ceiling lights. There are people around you, but no immediate walking hazards like stairs or obstacles are visible directly in front of you. Be cautious of the people around as you move.", "time": "2026-05-02T19:14:52.609720+00:00"}, {"type": "vision", "description": "You are in a room with several people around you. There are no immediate hazards directly in front of you.", "time": "2026-05-02T19:15:00.282175+00:00"}, {"type": "geofence", "description": "⚠️ LEFT SAFE ZONE — Home (680051m away)", "lat": "22.61488371211188", "lon": "75.88859881660657", "time": "2026-05-02T19:15:29.100645+00:00"}, {"type": "vision", "description": "This is a 50 rupee note.", "time": "2026-05-02T19:15:31.520856+00:00"}, {"type": "vision", "description": "You are in a room with white walls and ceiling lights. There are people around you, but no immediate walking hazards are visible directly in front of you. You appear to have some open space to move forward.", "time": "2026-05-02T19:16:06.428440+00:00"}, {"type": "vision", "description": "There is no Indian currency note visible in this image.", "time": "2026-05-02T19:16:13.350635+00:00"}, {"type": "classroom", "priority": "IMPORTANT", "summary": "Teacher emphasizes importance", "description": "[IMPORTANT] Teacher emphasizes importance", "transcript": ". . . . . This is really important. This is really important. Hello. Hello. Hello. One, two, three, one,", "time": "2026-05-02T19:22:49.575827+00:00"}, {"type": "classroom", "priority": "SKIP", "summary": "irrelevant utterance", "description": "[SKIP] irrelevant utterance", "transcript": "Yeah.", "time": "2026-05-02T19:23:01.997713+00:00"}, {"type": "classroom", "priority": "NOTES", "summary": "Lecture starts with a pause", "description": "[NOTES] Lecture starts with a pause", "transcript": "Well,", "time": "2026-05-02T19:23:26.824828+00:00"}, {"type": "vision", "description": "You are in a room with white walls and a yellow stripe on the ceiling. There are people around you, and it appears to be a crowded space, but there are no immediate hazards like stairs or obstacles directly in front of you.", "time": "2026-05-02T19:24:09.357497+00:00"}, {"type": "vision", "description": "You are in a room with several people around you. There are no immediate hazards like stairs or obstacles directly in front of you.", "time": "2026-05-02T19:34:04.672717+00:00"}, {"type": "vision", "description": "I'm showing you 5 fingers. Are you trying to communicate something specific?", "time": "2026-05-02T19:34:18.359479+00:00"}, {"type": "vision", "description": "I see 5 fingers. This looks similar to the scene from 0 minutes ago.", "time": "2026-05-02T19:34:27.685957+00:00"}, {"type": "geofence", "description": "⚠️ LEFT SAFE ZONE — Home (748225m away)", "lat": "22.032373", "lon": "75.657845", "time": "2026-05-02T19:34:32.377162+00:00"}, {"type": "classroom", "priority": "IMPORTANT", "summary": "Accessibility companion app explained", "description": "[IMPORTANT] Accessibility companion app explained", "transcript": "In its chunk, it is converting speech to text and making an activity log. Next, whatever you say is important for 60 seconds. That's the last thing related to it. So, it will record it. It is recording here as well. If you say something to it, it will know. I can't see it. It is recording. For example, we are in a hackathon where we are building accessibility companion. This is a very important problem statement. So, as soon as the timer is completed, the activity log will go directly to the Guardian. Now, all these things will be stored in it. like the vision that we are showing will be visible in the SOS all the general alerts will be visible", "time": "2026-05-02T19:37:12.366015+00:00"}, {"type": "vision", "description": "You are in a room with white walls and a ceiling fan. There are two men in front of you, one wearing a blue shirt and the other wearing a tan shirt. There are no immediate hazards like stairs or obstacles directly in front of you.", "time": "2026-05-02T19:51:32.088912+00:00"}, {"type": "vision", "description": "The person in front of you is showing 5 fingers. This looks similar to the area you were in a few minutes ago, with white walls and a ceiling fan.", "time": "2026-05-02T19:51:49.920756+00:00"}, {"type": "vision", "description": "I see 4 fingers. This looks similar to the area you were in a few minutes ago, with white walls and a ceiling fan.", "time": "2026-05-02T19:51:52.097880+00:00"}, {"type": "geofence", "description": "⚠️ LEFT SAFE ZONE — Home (680051m away)", "lat": "22.61488371211188", "lon": "75.88859881660657", "time": "2026-05-02T19:51:59.534881+00:00"}, {"type": "classroom", "priority": "IMPORTANT", "summary": "Test stopped unexpectedly", "description": "[IMPORTANT] Test stopped unexpectedly", "transcript": "I just started the test and it stopped", "time": "2026-05-02T19:53:26.902795+00:00"}, {"type": "vision", "description": "You are in a room with three people. There are no immediate hazards directly in front of you; the floor appears clear.", "time": "2026-05-02T19:53:55.179558+00:00"}, {"type": "geofence", "description": "⚠️ LEFT SAFE ZONE — Home (680053m away)", "lat": "22.614879424332152", "lon": "75.88852839345091", "time": "2026-05-02T19:54:22.848778+00:00"}, {"type": "vision", "description": "It seems like I'm not getting a clear view right now. Can you please move your camera or adjust the lighting so I can better assess your surroundings?", "time": "2026-05-02T20:02:18.504636+00:00"}, {"type": "geofence", "description": "⚠️ LEFT SAFE ZONE — Home (680053m away)", "lat": "22.614879424332152", "lon": "75.88852839345091", "time": "2026-05-02T20:02:45.718007+00:00"}, {"type": "geofence", "description": "⚠️ LEFT SAFE ZONE — Home (680053m away)", "lat": "22.6148798089316", "lon": "75.88852512436405", "time": "2026-05-02T20:08:15.690884+00:00"}, {"type": "geofence", "description": "⚠️ LEFT SAFE ZONE — Home (680053m away)", "lat": "22.6148798089316", "lon": "75.88852512436405", "time": "2026-05-02T20:13:46.193947+00:00"}, {"type": "geofence", "description": "⚠️ LEFT SAFE ZONE — Home (748222m away)", "lat": "22.032385", "lon": "75.657936", "time": "2026-05-02T20:18:45.680333+00:00"}, {"type": "geofence", "description": "⚠️ LEFT SAFE ZONE — Home (680051m away)", "lat": "22.61488371211188", "lon": "75.88859881660657", "time": "2026-05-02T20:24:15.677102+00:00"}, {"type": "geofence", "description": "⚠️ LEFT SAFE ZONE — Home (680051m away)", "lat": "22.61488371211188", "lon": "75.88859881660657", "time": "2026-05-02T20:29:45.645569+00:00"}, {"type": "vision", "description": "It seems like the camera view is not clear right now. Can you please move your camera or adjust the lighting so I can better assess your surroundings?", "time": "2026-05-02T20:34:33.297564+00:00"}, {"type": "geofence", "description": "⚠️ LEFT SAFE ZONE — Home (680051m away)", "lat": "22.61488371211188", "lon": "75.88859881660657", "time": "2026-05-02T20:34:45.678079+00:00"}, {"type": "vision", "description": "It seems like the camera view is not clear right now. Can you please move your camera or adjust the lighting so I can better assess your surroundings?", "time": "2026-05-02T20:34:52.947035+00:00"}, {"type": "vision", "description": "It seems like the camera view is not clear right now. Can you please move your camera or adjust the lighting so I can better assess your surroundings?", "time": "2026-05-02T20:34:56.681926+00:00"}, {"type": "vision", "description": "You are in a room with white walls and a ceiling. There are no immediate hazards directly in front of you, but I see two people, possibly near you. Please be cautious of their positions to avoid accidental contact.", "time": "2026-05-02T21:42:45.576055+00:00"}, {"type": "vision", "description": "You are in a room with white walls and ceiling lights. There are people around you, but no immediate obstacles or hazards like stairs are visible. You appear to have some clearance to move forward.", "time": "2026-05-02T21:44:57.049200+00:00"}, {"type": "geofence", "description": "⚠️ LEFT SAFE ZONE — Home (748225m away)", "lat": "22.032373", "lon": "75.657845", "time": "2026-05-02T21:45:25.466413+00:00"}, {"type": "classroom", "priority": "NOTES", "summary": "Speech to text conversion method", "description": "[NOTES] Speech to text conversion method", "transcript": "So, in 60 seconds, he will convert speech into text and will show you in the activity log what is happening. What are you using to convert speech into text?", "time": "2026-05-02T21:45:55.081959+00:00"}, {"type": "vision", "description": "You are in a room with a table directly in front of you. The table has various items, including wires, a bag, and tools, but no immediate walking hazards are visible.", "time": "2026-05-03T00:53:45.810857+00:00"}, {"type": "geofence", "description": "⚠️ LEFT SAFE ZONE — Home (748193m away)", "lat": "22.0327664", "lon": "75.6573311", "time": "2026-05-03T00:54:09.454405+00:00"}, {"type": "vision", "description": "The road ahead appears clear and flat, with a white car parked on the left side. You have a sidewalk to your right; trees line both sides of the road.", "time": "2026-05-03T01:05:05.467643+00:00"}, {"type": "geofence", "description": "⚠️ LEFT SAFE ZONE — Home (748238m away)", "lat": "22.0319363", "lon": "75.6595024", "time": "2026-05-03T01:05:33.869748+00:00"}, {"type": "vision", "description": "The area appears to be a playground with trees and a dirt path, which seems safe. However, I recommend watching your step on the uneven terrain and being mindful of any playground equipment.", "time": "2026-05-03T01:05:48.035660+00:00"}, {"type": "vision", "description": "The road ahead appears clear and flat, with a white car parked on the left side. There are two people walking ahead, and trees line both sides of the road; be cautious of the car and keep an eye on the path as you walk.", "time": "2026-05-03T01:06:01.616303+00:00"}, {"type": "vision", "description": "The road ahead appears clear and flat. There are two people walking ahead, and trees line both sides of the road; be cautious of the path as you walk. This looks similar to the area you were in 1 minute ago.", "time": "2026-05-03T01:06:21.225854+00:00"}, {"type": "vision", "description": "The path ahead appears clear and flat, with a dirt road stretching out before you. There are trees on both sides, but no immediate obstacles or hazards are visible. You can proceed forward with caution.", "time": "2026-05-03T01:40:05.841815+00:00"}, {"type": "vision", "description": "The path ahead appears clear and flat, with a dirt road stretching out before you. There are trees on both sides, but no immediate obstacles or hazards are visible. You can proceed forward with caution.", "time": "2026-05-03T01:40:25.585808+00:00"}, {"type": "geofence", "description": "⚠️ LEFT SAFE ZONE — Home (748374m away)", "lat": "22.0306454", "lon": "75.6597002", "time": "2026-05-03T01:40:34.025093+00:00"}, {"type": "vision", "description": "You are standing on a dirt path with dry leaves and twigs scattered around. The ground appears flat and clear of immediate obstacles. You can proceed forward with caution, similar to the area you were in 1 minute ago.", "time": "2026-05-03T01:40:41.769560+00:00"}, {"type": "vision", "description": "No obstacle directly ahead.", "time": "2026-05-03T02:03:23.548100+00:00"}, {"type": "vision", "description": "\"\"", "time": "2026-05-03T02:03:42.499114+00:00"}, {"type": "geofence", "description": "⚠️ LEFT SAFE ZONE — Home (748201m away)", "lat": "22.0326865", "lon": "75.6573451", "time": "2026-05-03T02:03:51.923907+00:00"}, {"type": "vision", "description": "Floor ahead.", "time": "2026-05-03T02:04:42.899138+00:00"}, {"type": "vision", "description": "\"\"", "time": "2026-05-03T02:05:08.553679+00:00"}, {"type": "vision", "description": "Wall directly ahead.", "time": "2026-05-03T02:05:41.364337+00:00"}, {"type": "vision", "description": "Door partially open to dark space ahead.", "time": "2026-05-03T02:06:03.118451+00:00"}, {"type": "vision", "description": "Wooden surface directly ahead.", "time": "2026-05-03T02:07:12.880148+00:00"}, {"type": "vision", "description": "Finger on right side.", "time": "2026-05-03T02:07:33.406034+00:00"}, {"type": "geofence", "description": "⚠️ LEFT SAFE ZONE — Home (748197m away)", "lat": "22.0327277", "lon": "75.6573243", "time": "2026-05-03T02:14:49.677696+00:00"}, {"type": "vision", "description": "Clear path ahead.", "time": "2026-05-03T02:17:46.058669+00:00"}, {"type": "vision", "description": "No immediate danger detected. Clear path ahead.", "time": "2026-05-03T02:19:49.826889+00:00"}, {"type": "vision", "description": "Table edge directly ahead. Low clearance under the table at your feet.", "time": "2026-05-03T02:20:01.303357+00:00"}, {"type": "vision", "description": "No immediate danger detected. Clear path ahead.", "time": "2026-05-03T02:20:03.605784+00:00"}, {"type": "vision", "description": "No immediate danger detected. Clear path ahead.", "time": "2026-05-03T02:28:56.395564+00:00"}, {"type": "geofence", "description": "⚠️ LEFT SAFE ZONE — Home (748198m away)", "lat": "22.0327178", "lon": "75.6573463", "time": "2026-05-03T02:29:25.830421+00:00"}, {"type": "vision", "description": "No immediate danger detected. Clear path ahead.", "time": "2026-05-03T02:29:38.565516+00:00"}, {"type": "vision", "description": "Wall to your right. Clear path ahead.", "time": "2026-05-03T02:30:04.317106+00:00"}, {"type": "vision", "description": "Stool directly ahead, may cause collision. Turn slightly right to avoid.", "time": "2026-05-03T02:30:40.888593+00:00"}, {"type": "vision", "description": "Clear path ahead. Floor is tile with a slight shine, potentially slippery.", "time": "2026-05-03T02:31:16.096310+00:00"}, {"type": "vision", "description": "Wall to your right, directly ahead seems clear. Floor change at your feet, shiny floor to the left, tile floor to the right.", "time": "2026-05-03T02:31:48.810834+00:00"}, {"type": "vision", "description": "Wall directly ahead. Turn for open path.", "time": "2026-05-03T02:34:19.124126+00:00"}, {"type": "vision", "description": "Wall directly ahead. Clear path to the side.", "time": "2026-05-03T02:34:50.679041+00:00"}, {"type": "geofence", "description": "⚠️ LEFT SAFE ZONE — Home (748206m away)", "lat": "22.0326656", "lon": "75.6572521", "time": "2026-05-03T02:34:55.887810+00:00"}, {"type": "vision", "description": "Clear path ahead. Floor changes slightly to your right.", "time": "2026-05-03T02:36:06.712776+00:00"}, {"type": "vision", "description": "Wall directly ahead. Proceed with caution.", "time": "2026-05-03T02:36:50.762954+00:00"}, {"type": "vision", "description": "Clear path ahead. Floor is tile with varying shades of gray.", "time": "2026-05-03T02:37:13.453238+00:00"}, {"type": "vision", "description": "Clear path ahead. You are on a smooth floor surface.", "time": "2026-05-03T03:05:01.240355+00:00"}, {"type": "geofence", "description": "⚠️ LEFT SAFE ZONE — Home (748200m away)", "lat": "22.032698", "lon": "75.6573492", "time": "2026-05-03T03:05:26.579611+00:00"}, {"type": "vision", "description": "No drop-off at your feet. Clear path ahead.", "time": "2026-05-03T03:05:42.476252+00:00"}, {"type": "vision", "description": "No drop-off at your feet. Clear path ahead.", "time": "2026-05-03T03:06:22.731450+00:00"}]